LICENSE.md
MANIFEST.in
README.md
requirements.txt
setup.py
target_encoding/__init__.py
target_encoding/target_encoding.py
target_encoding/utils.py
target_encoding.egg-info/PKG-INFO
target_encoding.egg-info/SOURCES.txt
target_encoding.egg-info/dependency_links.txt
target_encoding.egg-info/requires.txt
target_encoding.egg-info/top_level.txt