Metadata-Version: 2.1
Name: target-encoding
Version: 1.1.0
Summary: Module for target encoding
Home-page: https://github.com/KirillTushin/target_encoding
Author: Tushin Kirill
Author-email: tushin.ka@phystech.edu
License: MIT
Download-URL: https://github.com/KirillTushin/target_encoding
Platform: UNKNOWN
Classifier: Programming Language :: Python :: 3
Classifier: License :: OSI Approved :: MIT License
Classifier: Operating System :: OS Independent
License-File: LICENSE.md
